<?xml version="1.0" encoding="utf-8"?>

<root>
  <!--This is a config of dc_bi_mdm.org_organ_brand_detail-->
  <id>830</id>
  <taskType>100</taskType>
  <groupName>dc_bi_mdm</groupName>
  <triggerName>org_organ_brand_detail</triggerName>
  <sourceDbId>11</sourceDbId>
  <sourceParentTableId></sourceParentTableId>
  <sourceTable>org_organ_brand_detail</sourceTable>
  <dependencyTaskIds></dependencyTaskIds>
  <relationColumns>brand_no</relationColumns>
  <primaryKeys>brand_detail_no</primaryKeys>
  <selectColumns>brand_detail_id,brand_no,brand_detail_no,brand_detail_code,brand_detail_ename,brand_detail_cname,brand_category_no,special_code,affiliation,order_no,status,editor,edittm,createtm,edit_flag,remarks,ifnull(edittm:createtm) as yw_update_time</selectColumns>
  <specialColumnTypeList/>
  <syncTimeColumn>createtm,edittm</syncTimeColumn>
  <targetDbId>1</targetDbId>
  <targetTable>bi_mdm_org_organ_brand_detail</targetTable>
  <targetColumns/>
  <syncFreqSeconds>3600</syncFreqSeconds>
  <useSqlFlag>0</useSqlFlag>
  <isSlaveTable>0</isSlaveTable>
  <isOverwrite>1</isOverwrite>
  <isPhysicalDel>0</isPhysicalDel>
  <version>1.0</version>
  <subTaskList/>
</root>
